diana/__init__.py
diana_bio-0.0.0.dist-info/METADATA
diana_bio-0.0.0.dist-info/WHEEL
diana_bio-0.0.0.dist-info/top_level.txt
diana_bio-0.0.0.dist-info/RECORD
